clock_live-0.1.3.dist-info/licenses/LICENSE
liveclock/__init__.py
liveclock/core.py
liveclock/countdown.py
liveclock/locator.py
liveclock/zones.py
clock_live-0.1.3.dist-info/METADATA
clock_live-0.1.3.dist-info/WHEEL
clock_live-0.1.3.dist-info/top_level.txt
clock_live-0.1.3.dist-info/RECORD
