Metadata-Version: 2.4
Name: clock-live
Version: 0.1.3
Summary: A live timezone and countdown library with auto-location.
Author: TheLostIdea1
Classifier: Programming Language :: Python :: 3
Classifier: License :: OSI Approved :: MIT License
License-File: LICENSE
Requires-Dist: pytz
Requires-Dist: requests
Dynamic: author
Dynamic: classifier
Dynamic: description
Dynamic: description-content-type
Dynamic: license-file
Dynamic: requires-dist
Dynamic: summary
